{
  "generated_at": "2026-07-20T16:45:28.317373Z",
  "company_name": "현대자동차",
  "stock_code": "005380",
  "status": "partial",
  "last_successful_update": "2026-07-20T16:45:28.317373Z",
  "errors": [
    {
      "provider": "gdelt",
      "type": "HTTP429"
    }
  ],
  "news": [
    {
      "cluster_id": "2bdb8a96800a084f",
      "company_name": "현대자동차",
      "stock_code": "005380",
      "representative_title": "현대자동차 , 전북자치도·전북대와 피지컬 AI·로봇·에너지 등 첨단산...",
      "representative_url": "https://techholic.co.kr/news/articleView.html?idxno=222173",
      "representative_source": "techholic.co.kr",
      "representative_language": "Korean",
      "first_published_at": "2026-07-20T08:22:00Z",
      "last_published_at": "2026-07-20T08:22:00Z",
      "article_count": 1,
      "domestic_article_count": 1,
      "international_article_count": 0,
      "providers": [
        "naver"
      ],
      "source_domains": [
        "techholic.co.kr"
      ],
      "categories": [
        "기타"
      ],
      "event_keywords": [],
      "importance_score": 20,
      "importance_level": "low",
      "scoring_reasons": [
        "회사명이 제목에 정확히 등장 +10",
        "핵심 키워드 +5",
        "최근 24시간 +5"
      ],
      "needs_review": false,
      "articles": [
        {
          "title": "현대자동차 , 전북자치도·전북대와 피지컬 AI·로봇·에너지 등 첨단산...",
          "url": "https://techholic.co.kr/news/articleView.html?idxno=222173",
          "source": "techholic.co.kr",
          "source_domain": "techholic.co.kr",
          "published_at": "2026-07-20T17:22:00+09:00",
          "language": "Korean",
          "region": "domestic",
          "provider": "NAVER"
        }
      ]
    },
    {
      "cluster_id": "2ce82756d75df9dc",
      "company_name": "현대자동차",
      "stock_code": "005380",
      "representative_title": "현대자동차 , 전북자치도·전북대와 미래산업 인재육성 협력",
      "representative_url": "https://yna.co.kr/view/PYH20260720185600013?input=1196m",
      "representative_source": "yna.co.kr",
      "representative_language": "Korean",
      "first_published_at": "2026-07-20T08:20:00Z",
      "last_published_at": "2026-07-20T08:20:00Z",
      "article_count": 2,
      "domestic_article_count": 2,
      "international_article_count": 0,
      "providers": [
        "naver"
      ],
      "source_domains": [
        "newsdream.kr",
        "yna.co.kr"
      ],
      "categories": [
        "기타"
      ],
      "event_keywords": [],
      "importance_score": 35,
      "importance_level": "low",
      "scoring_reasons": [
        "Tier 1 출처 +20",
        "회사명이 제목에 정확히 등장 +10",
        "최근 24시간 +5"
      ],
      "needs_review": true,
      "articles": [
        {
          "title": "현대자동차 , 전북자치도·전북대와 미래산업 인재육성 협력",
          "url": "https://yna.co.kr/view/PYH20260720185600013?input=1196m",
          "source": "yna.co.kr",
          "source_domain": "yna.co.kr",
          "published_at": "2026-07-20T17:20:00+09:00",
          "language": "Korean",
          "region": "domestic",
          "provider": "NAVER"
        },
        {
          "title": "현대자동차 , 전북도·전북대와 미래산업 인재육성 협력 협약 체결",
          "url": "https://newsdream.kr/news/articleView.html?idxno=114714",
          "source": "newsdream.kr",
          "source_domain": "newsdream.kr",
          "published_at": "2026-07-20T17:20:00+09:00",
          "language": "Korean",
          "region": "domestic",
          "provider": "NAVER"
        }
      ]
    },
    {
      "cluster_id": "02fe13831054a3bc",
      "company_name": "현대자동차",
      "stock_code": "005380",
      "representative_title": "홀트아동복지회 부산지부· 현대자동차 노사, 울산 신생아 가정에 ‘H-희...",
      "representative_url": "https://segyebiz.com/newsView/20260720518968?OutUrl=naver",
      "representative_source": "segyebiz.com",
      "representative_language": "Korean",
      "first_published_at": "2026-07-20T08:00:00Z",
      "last_published_at": "2026-07-20T08:00:00Z",
      "article_count": 1,
      "domestic_article_count": 1,
      "international_article_count": 0,
      "providers": [
        "naver"
      ],
      "source_domains": [
        "segyebiz.com"
      ],
      "categories": [
        "기타"
      ],
      "event_keywords": [],
      "importance_score": 15,
      "importance_level": "low",
      "scoring_reasons": [
        "회사명이 제목에 정확히 등장 +10",
        "최근 24시간 +5"
      ],
      "needs_review": false,
      "articles": [
        {
          "title": "홀트아동복지회 부산지부· 현대자동차 노사, 울산 신생아 가정에 ‘H-희...",
          "url": "https://segyebiz.com/newsView/20260720518968?OutUrl=naver",
          "source": "segyebiz.com",
          "source_domain": "segyebiz.com",
          "published_at": "2026-07-20T17:00:00+09:00",
          "language": "Korean",
          "region": "domestic",
          "provider": "NAVER"
        }
      ]
    },
    {
      "cluster_id": "67ef0fd5bd0ff519",
      "company_name": "현대자동차",
      "stock_code": "005380",
      "representative_title": "李 대통령 \"새만금 현대자동차 그룹 투자 잠재력 가장 뛰어나\"…전북, ...",
      "representative_url": "https://domin.co.kr/news/articleView.html?idxno=1562201",
      "representative_source": "domin.co.kr",
      "representative_language": "Korean",
      "first_published_at": "2026-07-19T07:06:00Z",
      "last_published_at": "2026-07-19T07:06:00Z",
      "article_count": 1,
      "domestic_article_count": 1,
      "international_article_count": 0,
      "providers": [
        "naver"
      ],
      "source_domains": [
        "domin.co.kr"
      ],
      "categories": [
        "투자·생산"
      ],
      "event_keywords": [
        "investment"
      ],
      "importance_score": 30,
      "importance_level": "low",
      "scoring_reasons": [
        "회사명이 제목에 정확히 등장 +10",
        "최근 24시간 +5",
        "중요 사건 신호 +15"
      ],
      "needs_review": false,
      "articles": [
        {
          "title": "李 대통령 \"새만금 현대자동차 그룹 투자 잠재력 가장 뛰어나\"…전북, ...",
          "url": "https://domin.co.kr/news/articleView.html?idxno=1562201",
          "source": "domin.co.kr",
          "source_domain": "domin.co.kr",
          "published_at": "2026-07-19T16:06:00+09:00",
          "language": "Korean",
          "region": "domestic",
          "provider": "NAVER"
        }
      ]
    },
    {
      "cluster_id": "6334e0c4dddeea1a",
      "company_name": "현대자동차",
      "stock_code": "005380",
      "representative_title": "현대자동차 그룹, 여름 특별 무상점검 서비스 실시",
      "representative_url": "https://fetv.co.kr/news/articleView.html?idxno=306644",
      "representative_source": "fetv.co.kr",
      "representative_language": "Korean",
      "first_published_at": "2026-07-18T01:16:00Z",
      "last_published_at": "2026-07-18T01:16:00Z",
      "article_count": 1,
      "domestic_article_count": 1,
      "international_article_count": 0,
      "providers": [
        "naver"
      ],
      "source_domains": [
        "fetv.co.kr"
      ],
      "categories": [
        "기타"
      ],
      "event_keywords": [],
      "importance_score": 15,
      "importance_level": "low",
      "scoring_reasons": [
        "회사명이 제목에 정확히 등장 +10",
        "최근 24시간 +5"
      ],
      "needs_review": false,
      "articles": [
        {
          "title": "현대자동차 그룹, 여름 특별 무상점검 서비스 실시",
          "url": "https://fetv.co.kr/news/articleView.html?idxno=306644",
          "source": "fetv.co.kr",
          "source_domain": "fetv.co.kr",
          "published_at": "2026-07-18T10:16:00+09:00",
          "language": "Korean",
          "region": "domestic",
          "provider": "NAVER"
        }
      ]
    },
    {
      "cluster_id": "ab1e3e0971a25882",
      "company_name": "현대자동차",
      "stock_code": "005380",
      "representative_title": "현대자동차 그룹, 보스턴다이나믹스 지분 100% 인수 검토",
      "representative_url": "https://srtimes.kr/news/articleView.html?idxno=207741",
      "representative_source": "srtimes.kr",
      "representative_language": "Korean",
      "first_published_at": "2026-07-16T09:10:00Z",
      "last_published_at": "2026-07-16T09:10:00Z",
      "article_count": 1,
      "domestic_article_count": 1,
      "international_article_count": 0,
      "providers": [
        "naver"
      ],
      "source_domains": [
        "srtimes.kr"
      ],
      "categories": [
        "공급·규제",
        "인사·M&A"
      ],
      "event_keywords": [
        "m_and_a"
      ],
      "importance_score": 25,
      "importance_level": "low",
      "scoring_reasons": [
        "회사명이 제목에 정확히 등장 +10",
        "중요 사건 신호 +15"
      ],
      "needs_review": false,
      "articles": [
        {
          "title": "현대자동차 그룹, 보스턴다이나믹스 지분 100% 인수 검토",
          "url": "https://srtimes.kr/news/articleView.html?idxno=207741",
          "source": "srtimes.kr",
          "source_domain": "srtimes.kr",
          "published_at": "2026-07-16T18:10:00+09:00",
          "language": "Korean",
          "region": "domestic",
          "provider": "NAVER"
        }
      ]
    }
  ]
}
