{
  "generated_at": "2026-07-21T16:08:24.060465Z",
  "company_name": "한미반도체",
  "stock_code": "042700",
  "status": "ok",
  "last_successful_update": "2026-07-21T16:08:24.060465Z",
  "errors": [],
  "news": [
    {
      "cluster_id": "325cf4673f348ce4",
      "company_name": "한미반도체",
      "stock_code": "042700",
      "representative_title": "한미반도체 , 테크인사이츠 선정 글로벌 우수 반도체 장비기업",
      "representative_url": "https://yna.co.kr/view/AKR20260716171100003?input=1195m",
      "representative_source": "yna.co.kr",
      "representative_language": "Korean",
      "first_published_at": "2026-07-17T22:00:00Z",
      "last_published_at": "2026-07-17T22:00:00Z",
      "article_count": 1,
      "domestic_article_count": 1,
      "international_article_count": 0,
      "providers": [
        "naver"
      ],
      "source_domains": [
        "yna.co.kr"
      ],
      "categories": [
        "기술·제품",
        "인사·M&A"
      ],
      "event_keywords": [
        "personnel"
      ],
      "importance_score": 50,
      "importance_level": "watch",
      "scoring_reasons": [
        "Tier 1 출처 +20",
        "회사명이 제목에 정확히 등장 +10",
        "최근 24시간 +5",
        "중요 사건 신호 +15"
      ],
      "needs_review": false,
      "articles": [
        {
          "title": "한미반도체 , 테크인사이츠 선정 글로벌 우수 반도체 장비기업",
          "url": "https://yna.co.kr/view/AKR20260716171100003?input=1195m",
          "source": "yna.co.kr",
          "source_domain": "yna.co.kr",
          "published_at": "2026-07-18T07:00:00+09:00",
          "language": "Korean",
          "region": "domestic",
          "provider": "NAVER"
        }
      ]
    },
    {
      "cluster_id": "3416074133db27d7",
      "company_name": "한미반도체",
      "stock_code": "042700",
      "representative_title": "[더벨][Company Watch] '영업이익률 52%' 한미반도체 , 어닝 서프라이즈",
      "representative_url": "https://thebell.co.kr/free/content/ArticleView.asp?key=202607141458308880103865",
      "representative_source": "thebell.co.kr",
      "representative_language": "Korean",
      "first_published_at": "2026-07-15T22:02:00Z",
      "last_published_at": "2026-07-15T22:02:00Z",
      "article_count": 1,
      "domestic_article_count": 1,
      "international_article_count": 0,
      "providers": [
        "naver"
      ],
      "source_domains": [
        "thebell.co.kr"
      ],
      "categories": [
        "공급·규제",
        "기술·제품",
        "실적"
      ],
      "event_keywords": [
        "earnings"
      ],
      "importance_score": 45,
      "importance_level": "watch",
      "scoring_reasons": [
        "Tier 1 출처 +20",
        "회사명이 제목에 정확히 등장 +10",
        "중요 사건 신호 +15"
      ],
      "needs_review": false,
      "articles": [
        {
          "title": "[더벨][Company Watch] '영업이익률 52%' 한미반도체 , 어닝 서프라이즈",
          "url": "https://thebell.co.kr/free/content/ArticleView.asp?key=202607141458308880103865",
          "source": "thebell.co.kr",
          "source_domain": "thebell.co.kr",
          "published_at": "2026-07-16T07:02:00+09:00",
          "language": "Korean",
          "region": "domestic",
          "provider": "NAVER"
        }
      ]
    },
    {
      "cluster_id": "83aea68620ce02d1",
      "company_name": "한미반도체",
      "stock_code": "042700",
      "representative_title": "\"반도체장비도 공급 부족… 한미반도체 , 8공장 추진\"",
      "representative_url": "https://mk.co.kr/article/12099492",
      "representative_source": "mk.co.kr",
      "representative_language": "Korean",
      "first_published_at": "2026-07-15T08:49:00Z",
      "last_published_at": "2026-07-15T08:49:00Z",
      "article_count": 1,
      "domestic_article_count": 1,
      "international_article_count": 0,
      "providers": [
        "naver"
      ],
      "source_domains": [
        "mk.co.kr"
      ],
      "categories": [
        "공급·규제",
        "기술·제품",
        "투자·생산"
      ],
      "event_keywords": [
        "production",
        "supply"
      ],
      "importance_score": 45,
      "importance_level": "watch",
      "scoring_reasons": [
        "Tier 1 출처 +20",
        "회사명이 제목에 정확히 등장 +10",
        "중요 사건 신호 +15"
      ],
      "needs_review": false,
      "articles": [
        {
          "title": "\"반도체장비도 공급 부족… 한미반도체 , 8공장 추진\"",
          "url": "https://mk.co.kr/article/12099492",
          "source": "mk.co.kr",
          "source_domain": "mk.co.kr",
          "published_at": "2026-07-15T17:49:00+09:00",
          "language": "Korean",
          "region": "domestic",
          "provider": "NAVER"
        }
      ]
    },
    {
      "cluster_id": "9e755a992827c1cb",
      "company_name": "한미반도체",
      "stock_code": "042700",
      "representative_title": "한미반도체 , 2분기 매출 2511억원…최대 분기 실적 경신",
      "representative_url": "https://etnews.com/20260714000274",
      "representative_source": "etnews.com",
      "representative_language": "Korean",
      "first_published_at": "2026-07-14T02:52:00Z",
      "last_published_at": "2026-07-15T03:24:00Z",
      "article_count": 25,
      "domestic_article_count": 25,
      "international_article_count": 0,
      "providers": [
        "naver"
      ],
      "source_domains": [
        "ajunews.com",
        "biz.chosun.com",
        "biz.sbs.co.kr",
        "bloter.net",
        "daily.hankooki.com",
        "ddaily.co.kr",
        "dealsite.co.kr",
        "enewstoday.co.kr",
        "etnews.com",
        "globalepic.co.kr",
        "greened.kr",
        "hankookilbo.com",
        "hansbiz.co.kr",
        "inews24.com",
        "kdpress.co.kr",
        "mk.co.kr",
        "mt.co.kr",
        "news.bizwatch.co.kr",
        "news.mtn.co.kr",
        "pinpointnews.co.kr",
        "srtimes.kr",
        "the-biz.co.kr",
        "the-stock.kr",
        "weekly.hankooki.com"
      ],
      "categories": [
        "공급·규제",
        "기술·제품",
        "실적",
        "인사·M&A",
        "투자·생산"
      ],
      "event_keywords": [
        " 1300억",
        " 1303억",
        " 2510억",
        " 2511억",
        "511억",
        "earnings",
        "hbm",
        "investment",
        "m_and_a"
      ],
      "importance_score": 50,
      "importance_level": "watch",
      "scoring_reasons": [
        "Tier 1 출처 +20",
        "회사명이 제목에 정확히 등장 +10",
        "핵심 키워드 +5",
        "중요 사건 신호 +15"
      ],
      "needs_review": false,
      "articles": [
        {
          "title": "한미반도체 , 2분기 매출 2510억…\"사상 최대\"",
          "url": "https://weekly.hankooki.com/news/articleView.html?idxno=7174400",
          "source": "weekly.hankooki.com",
          "source_domain": "weekly.hankooki.com",
          "published_at": "2026-07-15T12:24:00+09:00",
          "language": "Korean",
          "region": "domestic",
          "provider": "NAVER"
        },
        {
          "title": "[특징주] 한미반도체 , HBM 훈풍에 '깜짝 실적'…26%대 급등",
          "url": "https://ajunews.com/view/20260715103012762",
          "source": "ajunews.com",
          "source_domain": "ajunews.com",
          "published_at": "2026-07-15T10:34:00+09:00",
          "language": "Korean",
          "region": "domestic",
          "provider": "NAVER"
        },
        {
          "title": "' HBM 수혜' 한미반도체 … 2분기 창사후 최대 실적",
          "url": "https://mk.co.kr/article/12098500",
          "source": "mk.co.kr",
          "source_domain": "mk.co.kr",
          "published_at": "2026-07-14T17:46:00+09:00",
          "language": "Korean",
          "region": "domestic",
          "provider": "NAVER"
        },
        {
          "title": "한미반도체 2분기 매출액 2511억원…역대 분기 최대",
          "url": "https://srtimes.kr/news/articleView.html?idxno=207548",
          "source": "srtimes.kr",
          "source_domain": "srtimes.kr",
          "published_at": "2026-07-14T17:36:00+09:00",
          "language": "Korean",
          "region": "domestic",
          "provider": "NAVER"
        },
        {
          "title": "한미반도체 , 2분기 매출 2511억원…창사 이래 최대",
          "url": "https://daily.hankooki.com/news/articleView.html?idxno=1385906",
          "source": "daily.hankooki.com",
          "source_domain": "daily.hankooki.com",
          "published_at": "2026-07-14T16:16:00+09:00",
          "language": "Korean",
          "region": "domestic",
          "provider": "NAVER"
        },
        {
          "title": "한미반도체 , 2분기 영업익 1303억… HBM ·AI 패키징 쌍끌이",
          "url": "https://bloter.net/news/articleView.html?idxno=668051",
          "source": "bloter.net",
          "source_domain": "bloter.net",
          "published_at": "2026-07-14T16:07:00+09:00",
          "language": "Korean",
          "region": "domestic",
          "provider": "NAVER"
        },
        {
          "title": "한미반도체 2분기 매출 2511억원 '사상 최고'",
          "url": "https://globalepic.co.kr/view.php?ud=20260714154210462348439a4874_29",
          "source": "globalepic.co.kr",
          "source_domain": "globalepic.co.kr",
          "published_at": "2026-07-14T15:46:00+09:00",
          "language": "Korean",
          "region": "domestic",
          "provider": "NAVER"
        },
        {
          "title": "HBM 수혜 한미반도체 , 2분기 영업이익 역대 최대 1300억",
          "url": "https://mk.co.kr/article/12098288",
          "source": "mk.co.kr",
          "source_domain": "mk.co.kr",
          "published_at": "2026-07-14T15:43:00+09:00",
          "language": "Korean",
          "region": "domestic",
          "provider": "NAVER"
        },
        {
          "title": "한미반도체 , 2분기 매출 2511억…역대 최대",
          "url": "https://hansbiz.co.kr/news/articleView.html?idxno=850241",
          "source": "hansbiz.co.kr",
          "source_domain": "hansbiz.co.kr",
          "published_at": "2026-07-14T15:32:00+09:00",
          "language": "Korean",
          "region": "domestic",
          "provider": "NAVER"
        },
        {
          "title": "한미반도체 2분기 매출 역대 최대 2511억... \"장비 업계 최고 수준\"",
          "url": "https://hankookilbo.com/news/article/A2026071414110002352?did=NA",
          "source": "hankookilbo.com",
          "source_domain": "hankookilbo.com",
          "published_at": "2026-07-14T15:00:00+09:00",
          "language": "Korean",
          "region": "domestic",
          "provider": "NAVER"
        },
        {
          "title": "한미반도체 , 2분기 매출 2511억원···역대 최대 분기 매출 기록",
          "url": "https://enewstoday.co.kr/news/articleView.html?idxno=2448656",
          "source": "enewstoday.co.kr",
          "source_domain": "enewstoday.co.kr",
          "published_at": "2026-07-14T14:48:00+09:00",
          "language": "Korean",
          "region": "domestic",
          "provider": "NAVER"
        },
        {
          "title": "한미반도체 , 2분기 매출 2천511억…역대 최대 분기 실적",
          "url": "https://biz.sbs.co.kr/article_hub/20000322406?division=NAVER",
          "source": "biz.sbs.co.kr",
          "source_domain": "biz.sbs.co.kr",
          "published_at": "2026-07-14T14:37:00+09:00",
          "language": "Korean",
          "region": "domestic",
          "provider": "NAVER"
        },
        {
          "title": "한미반도체 , 2분기 영업익 1303억원… HBM 장비가 견인",
          "url": "https://the-biz.co.kr/news/articleView.html?idxno=724406",
          "source": "the-biz.co.kr",
          "source_domain": "the-biz.co.kr",
          "published_at": "2026-07-14T14:28:00+09:00",
          "language": "Korean",
          "region": "domestic",
          "provider": "NAVER"
        },
        {
          "title": "한미반도체 , 2분기 매출 2511억원 ‘역대 최대’… 영업이익률 51.9%",
          "url": "https://biz.chosun.com/it-science/ict/2026/07/14/L75WPNYOTJDDZGCVKQUY57NZJM",
          "source": "biz.chosun.com",
          "source_domain": "biz.chosun.com",
          "published_at": "2026-07-14T14:06:00+09:00",
          "language": "Korean",
          "region": "domestic",
          "provider": "NAVER"
        },
        {
          "title": "한미반도체 , 2Q 매출 2511억…창사 이래 최대 실적 달성",
          "url": "https://dealsite.co.kr/articles/165289",
          "source": "dealsite.co.kr",
          "source_domain": "dealsite.co.kr",
          "published_at": "2026-07-14T13:52:00+09:00",
          "language": "Korean",
          "region": "domestic",
          "provider": "NAVER"
        },
        {
          "title": "한미반도체 , 2분기 매출 2511억원 기록...창사 이래 최대",
          "url": "https://pinpointnews.co.kr/news/articleView.html?idxno=468314",
          "source": "pinpointnews.co.kr",
          "source_domain": "pinpointnews.co.kr",
          "published_at": "2026-07-14T13:46:00+09:00",
          "language": "Korean",
          "region": "domestic",
          "provider": "NAVER"
        },
        {
          "title": "한미반도체 , 분기 매출 '사상 최대'…' HBM 4' 효과",
          "url": "https://the-stock.kr/news/articleView.html?idxno=32954",
          "source": "the-stock.kr",
          "source_domain": "the-stock.kr",
          "published_at": "2026-07-14T13:40:00+09:00",
          "language": "Korean",
          "region": "domestic",
          "provider": "NAVER"
        },
        {
          "title": "한미반도체 , 2분기 매출 2511억원…최대 분기 실적 경신",
          "url": "https://etnews.com/20260714000274",
          "source": "etnews.com",
          "source_domain": "etnews.com",
          "published_at": "2026-07-14T13:28:00+09:00",
          "language": "Korean",
          "region": "domestic",
          "provider": "NAVER"
        },
        {
          "title": "HBM 슈퍼사이클 올라탄 한미반도체 …분기 최대 실적",
          "url": "https://news.bizwatch.co.kr/article/industry/2026/07/14/0010",
          "source": "news.bizwatch.co.kr",
          "source_domain": "news.bizwatch.co.kr",
          "published_at": "2026-07-14T13:24:00+09:00",
          "language": "Korean",
          "region": "domestic",
          "provider": "NAVER"
        },
        {
          "title": "한미반도체 , 2분기 영업이익 1303억원… HBM 타고 최대 실적",
          "url": "https://inews24.com/view/1985342",
          "source": "inews24.com",
          "source_domain": "inews24.com",
          "published_at": "2026-07-14T13:18:00+09:00",
          "language": "Korean",
          "region": "domestic",
          "provider": "NAVER"
        },
        {
          "title": "한미반도체 2분기 영업이익 1303억... 반도체 수요 증가에 실적 상승",
          "url": "https://kdpress.co.kr/news/articleView.html?idxno=206898",
          "source": "kdpress.co.kr",
          "source_domain": "kdpress.co.kr",
          "published_at": "2026-07-14T12:32:00+09:00",
          "language": "Korean",
          "region": "domestic",
          "provider": "NAVER"
        },
        {
          "title": "한미반도체 , 2분기 사상 최대 매출…AI 투자에 HBM 장비 수요 증가",
          "url": "https://news.mtn.co.kr/news-detail/2026071411480741591",
          "source": "news.mtn.co.kr",
          "source_domain": "news.mtn.co.kr",
          "published_at": "2026-07-14T12:04:00+09:00",
          "language": "Korean",
          "region": "domestic",
          "provider": "NAVER"
        },
        {
          "title": "한미반도체 , 2분기 영업익 전년비 51%↑… HBM 장비 수요 증가 '호실적'",
          "url": "https://greened.kr/news/articleView.html?idxno=345010",
          "source": "greened.kr",
          "source_domain": "greened.kr",
          "published_at": "2026-07-14T12:01:00+09:00",
          "language": "Korean",
          "region": "domestic",
          "provider": "NAVER"
        },
        {
          "title": "한미반도체 , 2분기 매출 2511억원 '사상 최대'… HBM 장비 수요 확대",
          "url": "https://ddaily.co.kr/page/view/2026071411214300568",
          "source": "ddaily.co.kr",
          "source_domain": "ddaily.co.kr",
          "published_at": "2026-07-14T11:53:00+09:00",
          "language": "Korean",
          "region": "domestic",
          "provider": "NAVER"
        },
        {
          "title": "한미반도체 , AI 반도체 투자로 2분기 매출 2511억 '창사 이래 최대'",
          "url": "https://mt.co.kr/industry/2026/07/15/2026071410551434360",
          "source": "mt.co.kr",
          "source_domain": "mt.co.kr",
          "published_at": "2026-07-14T11:52:00+09:00",
          "language": "Korean",
          "region": "domestic",
          "provider": "NAVER"
        }
      ]
    },
    {
      "cluster_id": "555e79c3b1ff29b3",
      "company_name": "한미반도체",
      "stock_code": "042700",
      "representative_title": "[ET특징주] 한미반도체 , 2분기 호실적에 상승세",
      "representative_url": "https://etnews.com/20260715000141",
      "representative_source": "etnews.com",
      "representative_language": "Korean",
      "first_published_at": "2026-07-15T01:17:00Z",
      "last_published_at": "2026-07-15T01:17:00Z",
      "article_count": 1,
      "domestic_article_count": 1,
      "international_article_count": 0,
      "providers": [
        "naver"
      ],
      "source_domains": [
        "etnews.com"
      ],
      "categories": [
        "기술·제품",
        "실적",
        "투자·생산"
      ],
      "event_keywords": [
        "earnings"
      ],
      "importance_score": 45,
      "importance_level": "watch",
      "scoring_reasons": [
        "Tier 1 출처 +20",
        "회사명이 제목에 정확히 등장 +10",
        "중요 사건 신호 +15"
      ],
      "needs_review": false,
      "articles": [
        {
          "title": "[ET특징주] 한미반도체 , 2분기 호실적에 상승세",
          "url": "https://etnews.com/20260715000141",
          "source": "etnews.com",
          "source_domain": "etnews.com",
          "published_at": "2026-07-15T10:17:00+09:00",
          "language": "Korean",
          "region": "domestic",
          "provider": "NAVER"
        }
      ]
    },
    {
      "cluster_id": "d304839acfb9b478",
      "company_name": "한미반도체",
      "stock_code": "042700",
      "representative_title": "[단독] 한미반도체 회장 “ HBM 장비 생산 더 속도낼것…올해 美법인 설립...",
      "representative_url": "https://mk.co.kr/article/12098918",
      "representative_source": "mk.co.kr",
      "representative_language": "Korean",
      "first_published_at": "2026-07-15T00:46:00Z",
      "last_published_at": "2026-07-15T00:46:00Z",
      "article_count": 1,
      "domestic_article_count": 1,
      "international_article_count": 0,
      "providers": [
        "naver"
      ],
      "source_domains": [
        "mk.co.kr"
      ],
      "categories": [
        "공급·규제",
        "기술·제품",
        "투자·생산"
      ],
      "event_keywords": [
        "executive",
        "hbm",
        "production"
      ],
      "importance_score": 50,
      "importance_level": "watch",
      "scoring_reasons": [
        "Tier 1 출처 +20",
        "회사명이 제목에 정확히 등장 +10",
        "핵심 키워드 +5",
        "중요 사건 신호 +15"
      ],
      "needs_review": false,
      "articles": [
        {
          "title": "[단독] 한미반도체 회장 “ HBM 장비 생산 더 속도낼것…올해 美법인 설립...",
          "url": "https://mk.co.kr/article/12098918",
          "source": "mk.co.kr",
          "source_domain": "mk.co.kr",
          "published_at": "2026-07-15T09:46:00+09:00",
          "language": "Korean",
          "region": "domestic",
          "provider": "NAVER"
        }
      ]
    },
    {
      "cluster_id": "64bf10dcf758fab0",
      "company_name": "한미반도체",
      "stock_code": "042700",
      "representative_title": "한미반도체 , 2분기 매출 2511억원 역대 최대",
      "representative_url": "https://zdnet.co.kr/view?no=20260714105543",
      "representative_source": "zdnet.co.kr",
      "representative_language": "Korean",
      "first_published_at": "2026-07-14T02:30:00Z",
      "last_published_at": "2026-07-14T02:45:00Z",
      "article_count": 2,
      "domestic_article_count": 2,
      "international_article_count": 0,
      "providers": [
        "gdelt"
      ],
      "source_domains": [
        "etoday.co.kr",
        "zdnet.co.kr"
      ],
      "categories": [
        "실적"
      ],
      "event_keywords": [
        " 2511억",
        "earnings"
      ],
      "importance_score": 45,
      "importance_level": "watch",
      "scoring_reasons": [
        "Tier 1 출처 +20",
        "회사명이 제목에 정확히 등장 +10",
        "중요 사건 신호 +15"
      ],
      "needs_review": false,
      "articles": [
        {
          "title": "한미반도체 , 2분기 매출 2511억 역대 최대 … 영업이익률 51 . 9 %",
          "url": "https://etoday.co.kr/news/view/2603489",
          "source": "etoday.co.kr",
          "source_domain": "etoday.co.kr",
          "published_at": "2026-07-14T02:45:00Z",
          "language": "Korean",
          "region": "domestic",
          "provider": "GDELT"
        },
        {
          "title": "한미반도체 , 2분기 매출 2511억원 역대 최대",
          "url": "https://zdnet.co.kr/view?no=20260714105543",
          "source": "zdnet.co.kr",
          "source_domain": "zdnet.co.kr",
          "published_at": "2026-07-14T02:30:00Z",
          "language": "Korean",
          "region": "domestic",
          "provider": "GDELT"
        }
      ]
    },
    {
      "cluster_id": "e1b854e625968cf8",
      "company_name": "한미반도체",
      "stock_code": "042700",
      "representative_title": "한미반도체 , 5000평 8공장 품는다…'장비 쇼티지' 선제 대응",
      "representative_url": "https://newspim.com/news/view/20260720000985",
      "representative_source": "newspim.com",
      "representative_language": "Korean",
      "first_published_at": "2026-07-20T08:54:00Z",
      "last_published_at": "2026-07-20T08:54:00Z",
      "article_count": 1,
      "domestic_article_count": 1,
      "international_article_count": 0,
      "providers": [
        "naver"
      ],
      "source_domains": [
        "newspim.com"
      ],
      "categories": [
        "공급·규제",
        "기술·제품",
        "투자·생산"
      ],
      "event_keywords": [
        "production"
      ],
      "importance_score": 30,
      "importance_level": "low",
      "scoring_reasons": [
        "회사명이 제목에 정확히 등장 +10",
        "최근 24시간 +5",
        "중요 사건 신호 +15"
      ],
      "needs_review": false,
      "articles": [
        {
          "title": "한미반도체 , 5000평 8공장 품는다…'장비 쇼티지' 선제 대응",
          "url": "https://newspim.com/news/view/20260720000985",
          "source": "newspim.com",
          "source_domain": "newspim.com",
          "published_at": "2026-07-20T17:54:00+09:00",
          "language": "Korean",
          "region": "domestic",
          "provider": "NAVER"
        }
      ]
    },
    {
      "cluster_id": "12988b9eaa12f616",
      "company_name": "한미반도체",
      "stock_code": "042700",
      "representative_title": "한미반도체 , '창사 최대' 8공장 추진…AI 반도체 슈퍼사이클 선제 대응",
      "representative_url": "https://inews24.com/view/1986974",
      "representative_source": "inews24.com",
      "representative_language": "Korean",
      "first_published_at": "2026-07-20T07:38:00Z",
      "last_published_at": "2026-07-20T07:38:00Z",
      "article_count": 1,
      "domestic_article_count": 1,
      "international_article_count": 0,
      "providers": [
        "naver"
      ],
      "source_domains": [
        "inews24.com"
      ],
      "categories": [
        "기술·제품",
        "투자·생산"
      ],
      "event_keywords": [
        "production"
      ],
      "importance_score": 30,
      "importance_level": "low",
      "scoring_reasons": [
        "회사명이 제목에 정확히 등장 +10",
        "최근 24시간 +5",
        "중요 사건 신호 +15"
      ],
      "needs_review": false,
      "articles": [
        {
          "title": "한미반도체 , '창사 최대' 8공장 추진…AI 반도체 슈퍼사이클 선제 대응",
          "url": "https://inews24.com/view/1986974",
          "source": "inews24.com",
          "source_domain": "inews24.com",
          "published_at": "2026-07-20T16:38:00+09:00",
          "language": "Korean",
          "region": "domestic",
          "provider": "NAVER"
        }
      ]
    },
    {
      "cluster_id": "df10cf135cf4bd3f",
      "company_name": "한미반도체",
      "stock_code": "042700",
      "representative_title": "한미반도체 , 연말 2세대 하이브리드 본더 공개…2027년 공장 가동",
      "representative_url": "https://joseilbo.com/news/news_read.php?class=17&grp=&uid=572223",
      "representative_source": "joseilbo.com",
      "representative_language": "Korean",
      "first_published_at": "2026-07-20T06:40:00Z",
      "last_published_at": "2026-07-20T06:40:00Z",
      "article_count": 1,
      "domestic_article_count": 1,
      "international_article_count": 0,
      "providers": [
        "naver"
      ],
      "source_domains": [
        "joseilbo.com"
      ],
      "categories": [
        "기술·제품",
        "투자·생산"
      ],
      "event_keywords": [
        "production"
      ],
      "importance_score": 30,
      "importance_level": "low",
      "scoring_reasons": [
        "회사명이 제목에 정확히 등장 +10",
        "최근 24시간 +5",
        "중요 사건 신호 +15"
      ],
      "needs_review": false,
      "articles": [
        {
          "title": "한미반도체 , 연말 2세대 하이브리드 본더 공개…2027년 공장 가동",
          "url": "https://joseilbo.com/news/news_read.php?class=17&grp=&uid=572223",
          "source": "joseilbo.com",
          "source_domain": "joseilbo.com",
          "published_at": "2026-07-20T15:40:00+09:00",
          "language": "Korean",
          "region": "domestic",
          "provider": "NAVER"
        }
      ]
    },
    {
      "cluster_id": "139bd6659a427da7",
      "company_name": "한미반도체",
      "stock_code": "042700",
      "representative_title": "[속보] 한미반도체 , 기업가치 제고 계획 공시…\"2세대 하이브리드 본더...",
      "representative_url": "https://cbci.co.kr/news/articleView.html?idxno=590393",
      "representative_source": "cbci.co.kr",
      "representative_language": "Korean",
      "first_published_at": "2026-07-20T05:58:00Z",
      "last_published_at": "2026-07-20T05:58:00Z",
      "article_count": 1,
      "domestic_article_count": 1,
      "international_article_count": 0,
      "providers": [
        "naver"
      ],
      "source_domains": [
        "cbci.co.kr"
      ],
      "categories": [
        "기술·제품",
        "기타"
      ],
      "event_keywords": [],
      "importance_score": 15,
      "importance_level": "low",
      "scoring_reasons": [
        "회사명이 제목에 정확히 등장 +10",
        "최근 24시간 +5"
      ],
      "needs_review": false,
      "articles": [
        {
          "title": "[속보] 한미반도체 , 기업가치 제고 계획 공시…\"2세대 하이브리드 본더...",
          "url": "https://cbci.co.kr/news/articleView.html?idxno=590393",
          "source": "cbci.co.kr",
          "source_domain": "cbci.co.kr",
          "published_at": "2026-07-20T14:58:00+09:00",
          "language": "Korean",
          "region": "domestic",
          "provider": "NAVER"
        }
      ]
    },
    {
      "cluster_id": "4ec8a00e4ddd7a90",
      "company_name": "한미반도체",
      "stock_code": "042700",
      "representative_title": "한미반도체 , 8%대 급락…22만 원선으로 밀려 투자심리 위축",
      "representative_url": "https://job-post.co.kr/news/articleView.html?idxno=221606",
      "representative_source": "job-post.co.kr",
      "representative_language": "Korean",
      "first_published_at": "2026-07-20T05:30:00Z",
      "last_published_at": "2026-07-20T05:30:00Z",
      "article_count": 1,
      "domestic_article_count": 1,
      "international_article_count": 0,
      "providers": [
        "naver"
      ],
      "source_domains": [
        "job-post.co.kr"
      ],
      "categories": [
        "기술·제품",
        "주가·투자의견",
        "투자·생산"
      ],
      "event_keywords": [
        "investment"
      ],
      "importance_score": 30,
      "importance_level": "low",
      "scoring_reasons": [
        "회사명이 제목에 정확히 등장 +10",
        "최근 24시간 +5",
        "중요 사건 신호 +15"
      ],
      "needs_review": false,
      "articles": [
        {
          "title": "한미반도체 , 8%대 급락…22만 원선으로 밀려 투자심리 위축",
          "url": "https://job-post.co.kr/news/articleView.html?idxno=221606",
          "source": "job-post.co.kr",
          "source_domain": "job-post.co.kr",
          "published_at": "2026-07-20T14:30:00+09:00",
          "language": "Korean",
          "region": "domestic",
          "provider": "NAVER"
        }
      ]
    },
    {
      "cluster_id": "c2bfc763ecf1b673",
      "company_name": "한미반도체",
      "stock_code": "042700",
      "representative_title": "한미반도체 , 주가 22만원선까지 밀렸다…'양대지수 위축 흐름'",
      "representative_url": "https://cbci.co.kr/news/articleView.html?idxno=590362",
      "representative_source": "cbci.co.kr",
      "representative_language": "Korean",
      "first_published_at": "2026-07-20T04:34:00Z",
      "last_published_at": "2026-07-20T04:34:00Z",
      "article_count": 1,
      "domestic_article_count": 1,
      "international_article_count": 0,
      "providers": [
        "naver"
      ],
      "source_domains": [
        "cbci.co.kr"
      ],
      "categories": [
        "주가·투자의견",
        "투자·생산"
      ],
      "event_keywords": [],
      "importance_score": 0,
      "importance_level": "low",
      "scoring_reasons": [
        "회사명이 제목에 정확히 등장 +10",
        "최근 24시간 +5",
        "단순 주가·종목 추천 -25"
      ],
      "needs_review": false,
      "articles": [
        {
          "title": "한미반도체 , 주가 22만원선까지 밀렸다…'양대지수 위축 흐름'",
          "url": "https://cbci.co.kr/news/articleView.html?idxno=590362",
          "source": "cbci.co.kr",
          "source_domain": "cbci.co.kr",
          "published_at": "2026-07-20T13:34:00+09:00",
          "language": "Korean",
          "region": "domestic",
          "provider": "NAVER"
        }
      ]
    },
    {
      "cluster_id": "8e04760b5fed13fe",
      "company_name": "한미반도체",
      "stock_code": "042700",
      "representative_title": "한미반도체 , 글로벌 반도체 장비 고객만족 우수기업 선정",
      "representative_url": "https://news.tvchosun.com/site/data/html_dir/2026/07/18/2026071890077.html",
      "representative_source": "news.tvchosun.com",
      "representative_language": "Korean",
      "first_published_at": "2026-07-18T07:33:00Z",
      "last_published_at": "2026-07-18T07:33:00Z",
      "article_count": 1,
      "domestic_article_count": 1,
      "international_article_count": 0,
      "providers": [
        "naver"
      ],
      "source_domains": [
        "news.tvchosun.com"
      ],
      "categories": [
        "기술·제품",
        "인사·M&A"
      ],
      "event_keywords": [],
      "importance_score": 15,
      "importance_level": "low",
      "scoring_reasons": [
        "회사명이 제목에 정확히 등장 +10",
        "최근 24시간 +5"
      ],
      "needs_review": false,
      "articles": [
        {
          "title": "한미반도체 , 글로벌 반도체 장비 고객만족 우수기업 선정",
          "url": "https://news.tvchosun.com/site/data/html_dir/2026/07/18/2026071890077.html",
          "source": "news.tvchosun.com",
          "source_domain": "news.tvchosun.com",
          "published_at": "2026-07-18T16:33:00+09:00",
          "language": "Korean",
          "region": "domestic",
          "provider": "NAVER"
        }
      ]
    },
    {
      "cluster_id": "8b54942cd472bb04",
      "company_name": "한미반도체",
      "stock_code": "042700",
      "representative_title": "최근 5거래일 한미반도체 주가 변동성",
      "representative_url": "https://topstarnews.net/news/articleView.html?idxno=16138475",
      "representative_source": "topstarnews.net",
      "representative_language": "Korean",
      "first_published_at": "2026-07-18T01:06:00Z",
      "last_published_at": "2026-07-18T01:06:00Z",
      "article_count": 1,
      "domestic_article_count": 1,
      "international_article_count": 0,
      "providers": [
        "naver"
      ],
      "source_domains": [
        "topstarnews.net"
      ],
      "categories": [
        "주가·투자의견"
      ],
      "event_keywords": [],
      "importance_score": 0,
      "importance_level": "low",
      "scoring_reasons": [
        "회사명이 제목에 정확히 등장 +10",
        "최근 24시간 +5",
        "단순 주가·종목 추천 -25"
      ],
      "needs_review": false,
      "articles": [
        {
          "title": "최근 5거래일 한미반도체 주가 변동성",
          "url": "https://topstarnews.net/news/articleView.html?idxno=16138475",
          "source": "topstarnews.net",
          "source_domain": "topstarnews.net",
          "published_at": "2026-07-18T10:06:00+09:00",
          "language": "Korean",
          "region": "domestic",
          "provider": "NAVER"
        }
      ]
    },
    {
      "cluster_id": "2e8f12ac5000edc2",
      "company_name": "한미반도체",
      "stock_code": "042700",
      "representative_title": "한미반도체 , 글로벌 고객만족도 조사서 국내 장비업체 유일 선정",
      "representative_url": "https://mbnmoney.mbn.co.kr/news/view?news_no=MM1005881961",
      "representative_source": "mbnmoney.mbn.co.kr",
      "representative_language": "Korean",
      "first_published_at": "2026-07-18T00:40:00Z",
      "last_published_at": "2026-07-18T00:40:00Z",
      "article_count": 1,
      "domestic_article_count": 1,
      "international_article_count": 0,
      "providers": [
        "naver"
      ],
      "source_domains": [
        "mbnmoney.mbn.co.kr"
      ],
      "categories": [
        "공급·규제",
        "기술·제품",
        "인사·M&A"
      ],
      "event_keywords": [],
      "importance_score": 15,
      "importance_level": "low",
      "scoring_reasons": [
        "회사명이 제목에 정확히 등장 +10",
        "최근 24시간 +5"
      ],
      "needs_review": false,
      "articles": [
        {
          "title": "한미반도체 , 글로벌 고객만족도 조사서 국내 장비업체 유일 선정",
          "url": "https://mbnmoney.mbn.co.kr/news/view?news_no=MM1005881961",
          "source": "mbnmoney.mbn.co.kr",
          "source_domain": "mbnmoney.mbn.co.kr",
          "published_at": "2026-07-18T09:40:00+09:00",
          "language": "Korean",
          "region": "domestic",
          "provider": "NAVER"
        }
      ]
    },
    {
      "cluster_id": "582d9593808ab6b5",
      "company_name": "한미반도체",
      "stock_code": "042700",
      "representative_title": "한미반도체 주가 주루룩, 24만원선 초반으로 밀려…제헌절 휴장 이후 반...",
      "representative_url": "https://cbci.co.kr/news/articleView.html?idxno=589823",
      "representative_source": "cbci.co.kr",
      "representative_language": "Korean",
      "first_published_at": "2026-07-16T22:56:00Z",
      "last_published_at": "2026-07-16T22:56:00Z",
      "article_count": 1,
      "domestic_article_count": 1,
      "international_article_count": 0,
      "providers": [
        "naver"
      ],
      "source_domains": [
        "cbci.co.kr"
      ],
      "categories": [
        "주가·투자의견"
      ],
      "event_keywords": [],
      "importance_score": 0,
      "importance_level": "low",
      "scoring_reasons": [
        "회사명이 제목에 정확히 등장 +10",
        "최근 24시간 +5",
        "단순 주가·종목 추천 -25"
      ],
      "needs_review": false,
      "articles": [
        {
          "title": "한미반도체 주가 주루룩, 24만원선 초반으로 밀려…제헌절 휴장 이후 반...",
          "url": "https://cbci.co.kr/news/articleView.html?idxno=589823",
          "source": "cbci.co.kr",
          "source_domain": "cbci.co.kr",
          "published_at": "2026-07-17T07:56:00+09:00",
          "language": "Korean",
          "region": "domestic",
          "provider": "NAVER"
        }
      ]
    }
  ]
}
