{
  "company_name": "로보티즈",
  "stock_code": "108490",
  "updated_at": "2026-07-18T10:16:57.370394+09:00",
  "completion_status": "complete_8q",
  "quarter_count": 8,
  "missing_quarters": [],
  "current_basis": "unspecified",
  "quarters": [
    {
      "fiscal_quarter": "2024 Q2",
      "fiscal_year": 2024,
      "quarter_number": 2,
      "revenue": 8100000000,
      "operating_profit": 100000000,
      "net_income": -400000000,
      "revenue_raw": "81억",
      "operating_profit_raw": "1억",
      "net_income_raw": "-4억",
      "revenue_consensus": null,
      "operating_profit_consensus": null,
      "net_income_consensus": null,
      "current_or_historical": "historical",
      "source_status": "historical_reference",
      "provisional": null,
      "corrected": false,
      "consolidated_or_separate": "unspecified",
      "accounting_standard": null,
      "metric_basis": "reported_net_income",
      "disclosure_datetime": null,
      "dart_url": "https://dart.fss.or.kr/dsaf001/main.do?rcpNo=20260515002269",
      "source_history": [
        {
          "source_status": "historical_reference",
          "provisional": null,
          "corrected": false,
          "disclosure_datetime": null,
          "revenue": 8100000000,
          "operating_profit": 100000000,
          "net_income": -400000000,
          "dart_url": "https://dart.fss.or.kr/dsaf001/main.do?rcpNo=20260515002269"
        }
      ],
      "comparisons": {
        "revenue": {
          "qoq": {
            "percentage": null,
            "status": null
          },
          "yoy": {
            "percentage": null,
            "status": null
          }
        },
        "operating_profit": {
          "qoq": {
            "percentage": null,
            "status": null
          },
          "yoy": {
            "percentage": null,
            "status": null
          }
        },
        "net_income": {
          "qoq": {
            "percentage": null,
            "status": null
          },
          "yoy": {
            "percentage": null,
            "status": null
          }
        }
      }
    },
    {
      "fiscal_quarter": "2024 Q3",
      "fiscal_year": 2024,
      "quarter_number": 3,
      "revenue": 6800000000,
      "operating_profit": -1400000000,
      "net_income": -1500000000,
      "revenue_raw": "68억",
      "operating_profit_raw": "-14억",
      "net_income_raw": "-15억",
      "revenue_consensus": null,
      "operating_profit_consensus": null,
      "net_income_consensus": null,
      "current_or_historical": "historical",
      "source_status": "historical_reference",
      "provisional": null,
      "corrected": false,
      "consolidated_or_separate": "unspecified",
      "accounting_standard": null,
      "metric_basis": "reported_net_income",
      "disclosure_datetime": null,
      "dart_url": "https://dart.fss.or.kr/dsaf001/main.do?rcpNo=20260515002269",
      "source_history": [
        {
          "source_status": "historical_reference",
          "provisional": null,
          "corrected": false,
          "disclosure_datetime": null,
          "revenue": 6800000000,
          "operating_profit": -1400000000,
          "net_income": -1500000000,
          "dart_url": "https://dart.fss.or.kr/dsaf001/main.do?rcpNo=20260515002269"
        }
      ],
      "comparisons": {
        "revenue": {
          "qoq": {
            "percentage": -16.05,
            "status": null
          },
          "yoy": {
            "percentage": null,
            "status": null
          }
        },
        "operating_profit": {
          "qoq": {
            "percentage": null,
            "status": "적자전환"
          },
          "yoy": {
            "percentage": null,
            "status": null
          }
        },
        "net_income": {
          "qoq": {
            "percentage": null,
            "status": "적자확대"
          },
          "yoy": {
            "percentage": null,
            "status": null
          }
        }
      }
    },
    {
      "fiscal_quarter": "2024 Q4",
      "fiscal_year": 2024,
      "quarter_number": 4,
      "revenue": 6800000000,
      "operating_profit": -700000000,
      "net_income": 1500000000,
      "revenue_raw": "68억",
      "operating_profit_raw": "-7억",
      "net_income_raw": "15억",
      "revenue_consensus": null,
      "operating_profit_consensus": null,
      "net_income_consensus": null,
      "current_or_historical": "historical",
      "source_status": "historical_reference",
      "provisional": null,
      "corrected": false,
      "consolidated_or_separate": "unspecified",
      "accounting_standard": null,
      "metric_basis": "reported_net_income",
      "disclosure_datetime": null,
      "dart_url": "https://dart.fss.or.kr/dsaf001/main.do?rcpNo=20260515002269",
      "source_history": [
        {
          "source_status": "historical_reference",
          "provisional": null,
          "corrected": false,
          "disclosure_datetime": null,
          "revenue": 6800000000,
          "operating_profit": -700000000,
          "net_income": 1500000000,
          "dart_url": "https://dart.fss.or.kr/dsaf001/main.do?rcpNo=20260515002269"
        }
      ],
      "comparisons": {
        "revenue": {
          "qoq": {
            "percentage": 0.0,
            "status": null
          },
          "yoy": {
            "percentage": null,
            "status": null
          }
        },
        "operating_profit": {
          "qoq": {
            "percentage": null,
            "status": "적자축소"
          },
          "yoy": {
            "percentage": null,
            "status": null
          }
        },
        "net_income": {
          "qoq": {
            "percentage": null,
            "status": "흑자전환"
          },
          "yoy": {
            "percentage": null,
            "status": null
          }
        }
      }
    },
    {
      "fiscal_quarter": "2025 Q1",
      "fiscal_year": 2025,
      "quarter_number": 1,
      "revenue": 10200000000,
      "operating_profit": 800000000,
      "net_income": 1200000000,
      "revenue_raw": "102억",
      "operating_profit_raw": "8억",
      "net_income_raw": "12억",
      "revenue_consensus": null,
      "operating_profit_consensus": null,
      "net_income_consensus": null,
      "current_or_historical": "historical",
      "source_status": "historical_reference",
      "provisional": null,
      "corrected": false,
      "consolidated_or_separate": "unspecified",
      "accounting_standard": null,
      "metric_basis": "reported_net_income",
      "disclosure_datetime": null,
      "dart_url": "https://dart.fss.or.kr/dsaf001/main.do?rcpNo=20260515002269",
      "source_history": [
        {
          "source_status": "historical_reference",
          "provisional": null,
          "corrected": false,
          "disclosure_datetime": null,
          "revenue": 10200000000,
          "operating_profit": 800000000,
          "net_income": 1200000000,
          "dart_url": "https://dart.fss.or.kr/dsaf001/main.do?rcpNo=20260515002269"
        }
      ],
      "comparisons": {
        "revenue": {
          "qoq": {
            "percentage": 50.0,
            "status": null
          },
          "yoy": {
            "percentage": null,
            "status": null
          }
        },
        "operating_profit": {
          "qoq": {
            "percentage": null,
            "status": "흑자전환"
          },
          "yoy": {
            "percentage": null,
            "status": null
          }
        },
        "net_income": {
          "qoq": {
            "percentage": -20.0,
            "status": null
          },
          "yoy": {
            "percentage": null,
            "status": null
          }
        }
      }
    },
    {
      "fiscal_quarter": "2025 Q2",
      "fiscal_year": 2025,
      "quarter_number": 2,
      "revenue": 7900000000,
      "operating_profit": 200000000,
      "net_income": 200000000,
      "revenue_raw": "79억",
      "operating_profit_raw": "2억",
      "net_income_raw": "2억",
      "revenue_consensus": null,
      "operating_profit_consensus": null,
      "net_income_consensus": null,
      "current_or_historical": "historical",
      "source_status": "historical_reference",
      "provisional": null,
      "corrected": false,
      "consolidated_or_separate": "unspecified",
      "accounting_standard": null,
      "metric_basis": "reported_net_income",
      "disclosure_datetime": null,
      "dart_url": "https://dart.fss.or.kr/dsaf001/main.do?rcpNo=20260515002269",
      "source_history": [
        {
          "source_status": "historical_reference",
          "provisional": null,
          "corrected": false,
          "disclosure_datetime": null,
          "revenue": 7900000000,
          "operating_profit": 200000000,
          "net_income": 200000000,
          "dart_url": "https://dart.fss.or.kr/dsaf001/main.do?rcpNo=20260515002269"
        }
      ],
      "comparisons": {
        "revenue": {
          "qoq": {
            "percentage": -22.55,
            "status": null
          },
          "yoy": {
            "percentage": -2.47,
            "status": null
          }
        },
        "operating_profit": {
          "qoq": {
            "percentage": -75.0,
            "status": null
          },
          "yoy": {
            "percentage": 100.0,
            "status": null
          }
        },
        "net_income": {
          "qoq": {
            "percentage": -83.33,
            "status": null
          },
          "yoy": {
            "percentage": null,
            "status": "흑자전환"
          }
        }
      }
    },
    {
      "fiscal_quarter": "2025 Q3",
      "fiscal_year": 2025,
      "quarter_number": 3,
      "revenue": 9200000000,
      "operating_profit": 200000000,
      "net_income": 900000000,
      "revenue_raw": "92억",
      "operating_profit_raw": "2억",
      "net_income_raw": "9억",
      "revenue_consensus": null,
      "operating_profit_consensus": null,
      "net_income_consensus": null,
      "current_or_historical": "historical",
      "source_status": "historical_reference",
      "provisional": null,
      "corrected": false,
      "consolidated_or_separate": "unspecified",
      "accounting_standard": null,
      "metric_basis": "reported_net_income",
      "disclosure_datetime": null,
      "dart_url": "https://dart.fss.or.kr/dsaf001/main.do?rcpNo=20260515002269",
      "source_history": [
        {
          "source_status": "historical_reference",
          "provisional": null,
          "corrected": false,
          "disclosure_datetime": null,
          "revenue": 9200000000,
          "operating_profit": 200000000,
          "net_income": 900000000,
          "dart_url": "https://dart.fss.or.kr/dsaf001/main.do?rcpNo=20260515002269"
        }
      ],
      "comparisons": {
        "revenue": {
          "qoq": {
            "percentage": 16.46,
            "status": null
          },
          "yoy": {
            "percentage": 35.29,
            "status": null
          }
        },
        "operating_profit": {
          "qoq": {
            "percentage": 0.0,
            "status": null
          },
          "yoy": {
            "percentage": null,
            "status": "흑자전환"
          }
        },
        "net_income": {
          "qoq": {
            "percentage": 350.0,
            "status": null
          },
          "yoy": {
            "percentage": null,
            "status": "흑자전환"
          }
        }
      }
    },
    {
      "fiscal_quarter": "2025 Q4",
      "fiscal_year": 2025,
      "quarter_number": 4,
      "revenue": 11600000000,
      "operating_profit": 2100000000,
      "net_income": 3000000000,
      "revenue_raw": "116억",
      "operating_profit_raw": "21억",
      "net_income_raw": "30억",
      "revenue_consensus": null,
      "operating_profit_consensus": null,
      "net_income_consensus": null,
      "current_or_historical": "historical",
      "source_status": "historical_reference",
      "provisional": null,
      "corrected": false,
      "consolidated_or_separate": "unspecified",
      "accounting_standard": null,
      "metric_basis": "reported_net_income",
      "disclosure_datetime": null,
      "dart_url": "https://dart.fss.or.kr/dsaf001/main.do?rcpNo=20260515002269",
      "source_history": [
        {
          "source_status": "historical_reference",
          "provisional": null,
          "corrected": false,
          "disclosure_datetime": null,
          "revenue": 11600000000,
          "operating_profit": 2100000000,
          "net_income": 3000000000,
          "dart_url": "https://dart.fss.or.kr/dsaf001/main.do?rcpNo=20260515002269"
        }
      ],
      "comparisons": {
        "revenue": {
          "qoq": {
            "percentage": 26.09,
            "status": null
          },
          "yoy": {
            "percentage": 70.59,
            "status": null
          }
        },
        "operating_profit": {
          "qoq": {
            "percentage": 950.0,
            "status": null
          },
          "yoy": {
            "percentage": null,
            "status": "흑자전환"
          }
        },
        "net_income": {
          "qoq": {
            "percentage": 233.33,
            "status": null
          },
          "yoy": {
            "percentage": 100.0,
            "status": null
          }
        }
      }
    },
    {
      "fiscal_quarter": "2026 Q1",
      "fiscal_year": 2026,
      "quarter_number": 1,
      "revenue": 11800000000,
      "operating_profit": -11800000000,
      "net_income": -9900000000,
      "revenue_raw": "118억",
      "operating_profit_raw": "-118억",
      "net_income_raw": "-99억",
      "revenue_consensus": null,
      "operating_profit_consensus": null,
      "net_income_consensus": null,
      "current_or_historical": "current",
      "source_status": "final",
      "provisional": false,
      "corrected": false,
      "consolidated_or_separate": "unspecified",
      "accounting_standard": null,
      "metric_basis": "reported_net_income",
      "disclosure_datetime": null,
      "dart_url": "https://dart.fss.or.kr/dsaf001/main.do?rcpNo=20260515002269",
      "source_history": [
        {
          "source_status": "final",
          "provisional": false,
          "corrected": false,
          "disclosure_datetime": null,
          "revenue": 11800000000,
          "operating_profit": -11800000000,
          "net_income": -9900000000,
          "dart_url": "https://dart.fss.or.kr/dsaf001/main.do?rcpNo=20260515002269"
        }
      ],
      "comparisons": {
        "revenue": {
          "qoq": {
            "percentage": 1.72,
            "status": null
          },
          "yoy": {
            "percentage": 15.69,
            "status": null
          }
        },
        "operating_profit": {
          "qoq": {
            "percentage": null,
            "status": "적자전환"
          },
          "yoy": {
            "percentage": null,
            "status": "적자전환"
          }
        },
        "net_income": {
          "qoq": {
            "percentage": null,
            "status": "적자전환"
          },
          "yoy": {
            "percentage": null,
            "status": "적자전환"
          }
        }
      }
    }
  ],
  "source_count": 1,
  "warning_count": 0,
  "company": {
    "name": "로보티즈",
    "code": "108490",
    "market": "코스닥",
    "category": "로봇",
    "monitoringTier": "core",
    "completionStatus": "complete_8q",
    "missingQuarters": [],
    "currentBasis": "unspecified",
    "earnings": [
      {
        "period": "2024 Q2",
        "revenue": 81.0,
        "operatingIncome": 1.0,
        "netIncome": -4.0,
        "estimateRevenue": null,
        "estimateOperatingIncome": null,
        "estimateNetIncome": null,
        "provisional": null,
        "corrected": false,
        "sourceStatus": "historical_reference",
        "consolidatedOrSeparate": "unspecified",
        "dartUrl": "https://dart.fss.or.kr/dsaf001/main.do?rcpNo=20260515002269",
        "comparisons": {
          "revenue": {
            "qoq": {
              "percentage": null,
              "status": null
            },
            "yoy": {
              "percentage": null,
              "status": null
            }
          },
          "operating_profit": {
            "qoq": {
              "percentage": null,
              "status": null
            },
            "yoy": {
              "percentage": null,
              "status": null
            }
          },
          "net_income": {
            "qoq": {
              "percentage": null,
              "status": null
            },
            "yoy": {
              "percentage": null,
              "status": null
            }
          }
        }
      },
      {
        "period": "2024 Q3",
        "revenue": 68.0,
        "operatingIncome": -14.0,
        "netIncome": -15.0,
        "estimateRevenue": null,
        "estimateOperatingIncome": null,
        "estimateNetIncome": null,
        "provisional": null,
        "corrected": false,
        "sourceStatus": "historical_reference",
        "consolidatedOrSeparate": "unspecified",
        "dartUrl": "https://dart.fss.or.kr/dsaf001/main.do?rcpNo=20260515002269",
        "comparisons": {
          "revenue": {
            "qoq": {
              "percentage": -16.05,
              "status": null
            },
            "yoy": {
              "percentage": null,
              "status": null
            }
          },
          "operating_profit": {
            "qoq": {
              "percentage": null,
              "status": "적자전환"
            },
            "yoy": {
              "percentage": null,
              "status": null
            }
          },
          "net_income": {
            "qoq": {
              "percentage": null,
              "status": "적자확대"
            },
            "yoy": {
              "percentage": null,
              "status": null
            }
          }
        }
      },
      {
        "period": "2024 Q4",
        "revenue": 68.0,
        "operatingIncome": -7.0,
        "netIncome": 15.0,
        "estimateRevenue": null,
        "estimateOperatingIncome": null,
        "estimateNetIncome": null,
        "provisional": null,
        "corrected": false,
        "sourceStatus": "historical_reference",
        "consolidatedOrSeparate": "unspecified",
        "dartUrl": "https://dart.fss.or.kr/dsaf001/main.do?rcpNo=20260515002269",
        "comparisons": {
          "revenue": {
            "qoq": {
              "percentage": 0.0,
              "status": null
            },
            "yoy": {
              "percentage": null,
              "status": null
            }
          },
          "operating_profit": {
            "qoq": {
              "percentage": null,
              "status": "적자축소"
            },
            "yoy": {
              "percentage": null,
              "status": null
            }
          },
          "net_income": {
            "qoq": {
              "percentage": null,
              "status": "흑자전환"
            },
            "yoy": {
              "percentage": null,
              "status": null
            }
          }
        }
      },
      {
        "period": "2025 Q1",
        "revenue": 102.0,
        "operatingIncome": 8.0,
        "netIncome": 12.0,
        "estimateRevenue": null,
        "estimateOperatingIncome": null,
        "estimateNetIncome": null,
        "provisional": null,
        "corrected": false,
        "sourceStatus": "historical_reference",
        "consolidatedOrSeparate": "unspecified",
        "dartUrl": "https://dart.fss.or.kr/dsaf001/main.do?rcpNo=20260515002269",
        "comparisons": {
          "revenue": {
            "qoq": {
              "percentage": 50.0,
              "status": null
            },
            "yoy": {
              "percentage": null,
              "status": null
            }
          },
          "operating_profit": {
            "qoq": {
              "percentage": null,
              "status": "흑자전환"
            },
            "yoy": {
              "percentage": null,
              "status": null
            }
          },
          "net_income": {
            "qoq": {
              "percentage": -20.0,
              "status": null
            },
            "yoy": {
              "percentage": null,
              "status": null
            }
          }
        }
      },
      {
        "period": "2025 Q2",
        "revenue": 79.0,
        "operatingIncome": 2.0,
        "netIncome": 2.0,
        "estimateRevenue": null,
        "estimateOperatingIncome": null,
        "estimateNetIncome": null,
        "provisional": null,
        "corrected": false,
        "sourceStatus": "historical_reference",
        "consolidatedOrSeparate": "unspecified",
        "dartUrl": "https://dart.fss.or.kr/dsaf001/main.do?rcpNo=20260515002269",
        "comparisons": {
          "revenue": {
            "qoq": {
              "percentage": -22.55,
              "status": null
            },
            "yoy": {
              "percentage": -2.47,
              "status": null
            }
          },
          "operating_profit": {
            "qoq": {
              "percentage": -75.0,
              "status": null
            },
            "yoy": {
              "percentage": 100.0,
              "status": null
            }
          },
          "net_income": {
            "qoq": {
              "percentage": -83.33,
              "status": null
            },
            "yoy": {
              "percentage": null,
              "status": "흑자전환"
            }
          }
        }
      },
      {
        "period": "2025 Q3",
        "revenue": 92.0,
        "operatingIncome": 2.0,
        "netIncome": 9.0,
        "estimateRevenue": null,
        "estimateOperatingIncome": null,
        "estimateNetIncome": null,
        "provisional": null,
        "corrected": false,
        "sourceStatus": "historical_reference",
        "consolidatedOrSeparate": "unspecified",
        "dartUrl": "https://dart.fss.or.kr/dsaf001/main.do?rcpNo=20260515002269",
        "comparisons": {
          "revenue": {
            "qoq": {
              "percentage": 16.46,
              "status": null
            },
            "yoy": {
              "percentage": 35.29,
              "status": null
            }
          },
          "operating_profit": {
            "qoq": {
              "percentage": 0.0,
              "status": null
            },
            "yoy": {
              "percentage": null,
              "status": "흑자전환"
            }
          },
          "net_income": {
            "qoq": {
              "percentage": 350.0,
              "status": null
            },
            "yoy": {
              "percentage": null,
              "status": "흑자전환"
            }
          }
        }
      },
      {
        "period": "2025 Q4",
        "revenue": 116.0,
        "operatingIncome": 21.0,
        "netIncome": 30.0,
        "estimateRevenue": null,
        "estimateOperatingIncome": null,
        "estimateNetIncome": null,
        "provisional": null,
        "corrected": false,
        "sourceStatus": "historical_reference",
        "consolidatedOrSeparate": "unspecified",
        "dartUrl": "https://dart.fss.or.kr/dsaf001/main.do?rcpNo=20260515002269",
        "comparisons": {
          "revenue": {
            "qoq": {
              "percentage": 26.09,
              "status": null
            },
            "yoy": {
              "percentage": 70.59,
              "status": null
            }
          },
          "operating_profit": {
            "qoq": {
              "percentage": 950.0,
              "status": null
            },
            "yoy": {
              "percentage": null,
              "status": "흑자전환"
            }
          },
          "net_income": {
            "qoq": {
              "percentage": 233.33,
              "status": null
            },
            "yoy": {
              "percentage": 100.0,
              "status": null
            }
          }
        }
      },
      {
        "period": "2026 Q1",
        "revenue": 118.0,
        "operatingIncome": -118.0,
        "netIncome": -99.0,
        "estimateRevenue": null,
        "estimateOperatingIncome": null,
        "estimateNetIncome": null,
        "provisional": false,
        "corrected": false,
        "sourceStatus": "final",
        "consolidatedOrSeparate": "unspecified",
        "dartUrl": "https://dart.fss.or.kr/dsaf001/main.do?rcpNo=20260515002269",
        "comparisons": {
          "revenue": {
            "qoq": {
              "percentage": 1.72,
              "status": null
            },
            "yoy": {
              "percentage": 15.69,
              "status": null
            }
          },
          "operating_profit": {
            "qoq": {
              "percentage": null,
              "status": "적자전환"
            },
            "yoy": {
              "percentage": null,
              "status": "적자전환"
            }
          },
          "net_income": {
            "qoq": {
              "percentage": null,
              "status": "적자전환"
            },
            "yoy": {
              "percentage": null,
              "status": "적자전환"
            }
          }
        }
      }
    ],
    "news": []
  }
}
